Workbook

Sheet KPI Dashboard
A1: KPI | B1: Formula / source | C1: Target (Day 90) | D1: Actual | E1: RAG
A2: Prospects in CRM | B2: COUNTA('CRM Pipeline'!B2:B1000) | C2: 400 | D2: =COUNTA('CRM Pipeline'!B2:B1000) | E2: =IF(D2>=C2,"G",IF(D2>=0.7*C2,"A","R"))
A3: Contacted | B3: COUNTA('CRM Pipeline'!M2:M1000)-COUNTIF('CRM Pipeline'!M2:M1000,"1*") | C3: 300 | D3: =COUNTA('CRM Pipeline'!M2:M1000)-COUNTIF('CRM Pipeline'!M2:M1000,"1*") | E3: =IF(D3>=C3,"G",IF(D3>=0.7*C3,"A","R"))
A4: Reply rate % | B4: IFERROR((COUNTIF('CRM Pipeline'!M2:M1000,"3*")+COUNTIF('CRM Pipeline'!M2:M1000,"4*")+COUNTIF('CRM Pipeline'!M2:M1000,"5*")+COUNTIF('CRM Pipeline'!M2:M1000,"6*"))/(COUNTA('CRM Pipeline'!M2:M1000)-COUNTIF('CRM Pipeline'!M2:M1000,"1*")),0) | C4: 0.08 | D4: =IFERROR((COUNTIF('CRM Pipeline'!M2:M1000,"3*")+COUNTIF('CRM Pipeline'!M2:M1000,"4*")+COUNTIF('CRM Pipeline'!M2:M1000,"5*")+COUNTIF('CRM Pipeline'!M2:M1000,"6*"))/(COUNTA('CRM Pipeline'!M2:M1000)-COUNTIF('CRM Pipeline'!M2:M1000,"1*")),0) | E4: =IF(D4>=C4,"G",IF(D4>=0.7*C4,"A","R"))
A5: Discovery calls booked | B5: COUNTIF('CRM Pipeline'!M2:M1000,"4*")+COUNTIF('CRM Pipeline'!M2:M1000,"5*")+COUNTIF('CRM Pipeline'!M2:M1000,"6*") | C5: 12 | D5: =COUNTIF('CRM Pipeline'!M2:M1000,"4*")+COUNTIF('CRM Pipeline'!M2:M1000,"5*")+COUNTIF('CRM Pipeline'!M2:M1000,"6*") | E5: =IF(D5>=C5,"G",IF(D5>=0.7*C5,"A","R"))
A6: Deals won | B6: COUNTIF('CRM Pipeline'!M2:M1000,"6*") | C6: 4 | D6: =COUNTIF('CRM Pipeline'!M2:M1000,"6*") | E6: =IF(D6>=C6,"G",IF(D6>=0.7*C6,"A","R"))
A7: Weighted pipeline USD | B7: SUM('CRM Pipeline'!U2:U1000) | C7: 6000 | D7: =SUM('CRM Pipeline'!U2:U1000) | E7: =IF(D7>=C7,"G",IF(D7>=0.7*C7,"A","R"))
A8: Revenue to date USD (tracker) | B8: '90-Day Tracker'!J15 | C8: 3000 | D8: ='90-Day Tracker'!J15 | E8: =IF(D8>=C8,"G",IF(D8>=0.7*C8,"A","R"))
A9: Effective hourly rate USD | B9: IFERROR('90-Day Tracker'!J15/'90-Day Tracker'!K15,0) | C9: 25 | D9: =IFERROR('90-Day Tracker'!J15/'90-Day Tracker'!K15,0) | E9: =IF(D9>=C9,"G",IF(D9>=0.7*C9,"A","R"))
A10: Base-case cumulative profit M3 PKR | B10: Base!Q4 | C10: 0 | D10: =Base!Q4 | E10: =IF(D10>=C10,"G",IF(D10>=0.7*C10,"A","R"))
A12: Yellow cells on every sheet are inputs. Stage codes start with a digit (1-8); KPIs count stages with wildcard COUNTIF, e.g. "3*".

Sheet Assumptions
A1: Driver | B1: Value | C1: Note
A2: FX PKR per USD | B2: 280 | C2: ASSUMPTION - update monthly from SBP interbank
A3: Upwork fee % | B3: 0.1 | C3: ASSUMPTION - Upwork variable fee; check your contract
A4: Payment / FX cost % | B4: 0.02 | C4: Payoneer withdrawal + spread, ASSUMPTION
A5: One-off setup PKR (Month 1) | B5: 60000 | C5: Domain, site, NTN/PSEB, demo data, design
A6: Starting capital PKR | B6: 500000 | C6: Hard ceiling - do not exceed

Sheet Conservative
A1: Month | B1: Projects | C1: Avg project USD | D1: Retainers | E1: Avg retainer USD | F1: Upwork share | G1: Contractor PKR | H1: Software USD | I1: Marketing USD | J1: Paying customers | K1: Revenue PKR | L1: Avg rev/customer PKR | M1: Direct costs PKR | N1: Software/ops PKR | O1: Marketing PKR | P1: Net profit PKR | Q1: Cumulative profit PKR | R1: Cumulative investment PKR
A2: 1 | B2: 0 | C2: 0 | D2: 0 | E2: 0 | F2: 1 | G2: 0 | H2: 80 | I2: 40 | J2: =B2+D2 | K2: =(B2*C2+D2*E2)*Assumptions!$B$2 | L2: =IFERROR(K2/J2,0) | M2: =K2*(Assumptions!$B$3*F2+Assumptions!$B$4)+G2 | N2: =H2*Assumptions!$B$2+IF(A2=1,Assumptions!$B$5,0) | O2: =I2*Assumptions!$B$2 | P2: =K2-M2-N2-O2 | Q2: =P2 | R2: =MAX(0,-Q2)
A3: 2 | B3: 0 | C3: 0 | D3: 0 | E3: 0 | F3: 1 | G3: 0 | H3: 100 | I3: 60 | J3: =B3+D3 | K3: =(B3*C3+D3*E3)*Assumptions!$B$2 | L3: =IFERROR(K3/J3,0) | M3: =K3*(Assumptions!$B$3*F3+Assumptions!$B$4)+G3 | N3: =H3*Assumptions!$B$2+IF(A3=1,Assumptions!$B$5,0) | O3: =I3*Assumptions!$B$2 | P3: =K3-M3-N3-O3 | Q3: =Q2+P3 | R3: =MAX(R2,-Q3)
A4: 3 | B4: 1 | C4: 350 | D4: 0 | E4: 0 | F4: 1 | G4: 0 | H4: 100 | I4: 60 | J4: =B4+D4 | K4: =(B4*C4+D4*E4)*Assumptions!$B$2 | L4: =IFERROR(K4/J4,0) | M4: =K4*(Assumptions!$B$3*F4+Assumptions!$B$4)+G4 | N4: =H4*Assumptions!$B$2+IF(A4=1,Assumptions!$B$5,0) | O4: =I4*Assumptions!$B$2 | P4: =K4-M4-N4-O4 | Q4: =Q3+P4 | R4: =MAX(R3,-Q4)
A5: 4 | B5: 1 | C5: 450 | D5: 0 | E5: 0 | F5: 1 | G5: 0 | H5: 100 | I5: 60 | J5: =B5+D5 | K5: =(B5*C5+D5*E5)*Assumptions!$B$2 | L5: =IFERROR(K5/J5,0) | M5: =K5*(Assumptions!$B$3*F5+Assumptions!$B$4)+G5 | N5: =H5*Assumptions!$B$2+IF(A5=1,Assumptions!$B$5,0) | O5: =I5*Assumptions!$B$2 | P5: =K5-M5-N5-O5 | Q5: =Q4+P5 | R5: =MAX(R4,-Q5)
A6: 5 | B6: 1 | C6: 500 | D6: 1 | E6: 400 | F6: 0.9 | G6: 0 | H6: 100 | I6: 60 | J6: =B6+D6 | K6: =(B6*C6+D6*E6)*Assumptions!$B$2 | L6: =IFERROR(K6/J6,0) | M6: =K6*(Assumptions!$B$3*F6+Assumptions!$B$4)+G6 | N6: =H6*Assumptions!$B$2+IF(A6=1,Assumptions!$B$5,0) | O6: =I6*Assumptions!$B$2 | P6: =K6-M6-N6-O6 | Q6: =Q5+P6 | R6: =MAX(R5,-Q6)
A7: 6 | B7: 1 | C7: 550 | D7: 1 | E7: 400 | F7: 0.9 | G7: 0 | H7: 100 | I7: 60 | J7: =B7+D7 | K7: =(B7*C7+D7*E7)*Assumptions!$B$2 | L7: =IFERROR(K7/J7,0) | M7: =K7*(Assumptions!$B$3*F7+Assumptions!$B$4)+G7 | N7: =H7*Assumptions!$B$2+IF(A7=1,Assumptions!$B$5,0) | O7: =I7*Assumptions!$B$2 | P7: =K7-M7-N7-O7 | Q7: =Q6+P7 | R7: =MAX(R6,-Q7)
A8: 7 | B8: 1 | C8: 600 | D8: 1 | E8: 400 | F8: 0.8 | G8: 0 | H8: 100 | I8: 60 | J8: =B8+D8 | K8: =(B8*C8+D8*E8)*Assumptions!$B$2 | L8: =IFERROR(K8/J8,0) | M8: =K8*(Assumptions!$B$3*F8+Assumptions!$B$4)+G8 | N8: =H8*Assumptions!$B$2+IF(A8=1,Assumptions!$B$5,0) | O8: =I8*Assumptions!$B$2 | P8: =K8-M8-N8-O8 | Q8: =Q7+P8 | R8: =MAX(R7,-Q8)
A9: 8 | B9: 1 | C9: 600 | D9: 1 | E9: 400 | F9: 0.8 | G9: 0 | H9: 100 | I9: 60 | J9: =B9+D9 | K9: =(B9*C9+D9*E9)*Assumptions!$B$2 | L9: =IFERROR(K9/J9,0) | M9: =K9*(Assumptions!$B$3*F9+Assumptions!$B$4)+G9 | N9: =H9*Assumptions!$B$2+IF(A9=1,Assumptions!$B$5,0) | O9: =I9*Assumptions!$B$2 | P9: =K9-M9-N9-O9 | Q9: =Q8+P9 | R9: =MAX(R8,-Q9)
A10: 9 | B10: 1 | C10: 650 | D10: 2 | E10: 425 | F10: 0.7 | G10: 0 | H10: 100 | I10: 60 | J10: =B10+D10 | K10: =(B10*C10+D10*E10)*Assumptions!$B$2 | L10: =IFERROR(K10/J10,0) | M10: =K10*(Assumptions!$B$3*F10+Assumptions!$B$4)+G10 | N10: =H10*Assumptions!$B$2+IF(A10=1,Assumptions!$B$5,0) | O10: =I10*Assumptions!$B$2 | P10: =K10-M10-N10-O10 | Q10: =Q9+P10 | R10: =MAX(R9,-Q10)
A11: 10 | B11: 1 | C11: 650 | D11: 2 | E11: 425 | F11: 0.7 | G11: 0 | H11: 100 | I11: 60 | J11: =B11+D11 | K11: =(B11*C11+D11*E11)*Assumptions!$B$2 | L11: =IFERROR(K11/J11,0) | M11: =K11*(Assumptions!$B$3*F11+Assumptions!$B$4)+G11 | N11: =H11*Assumptions!$B$2+IF(A11=1,Assumptions!$B$5,0) | O11: =I11*Assumptions!$B$2 | P11: =K11-M11-N11-O11 | Q11: =Q10+P11 | R11: =MAX(R10,-Q11)
A12: 11 | B12: 1 | C12: 700 | D12: 2 | E12: 450 | F12: 0.7 | G12: 0 | H12: 100 | I12: 60 | J12: =B12+D12 | K12: =(B12*C12+D12*E12)*Assumptions!$B$2 | L12: =IFERROR(K12/J12,0) | M12: =K12*(Assumptions!$B$3*F12+Assumptions!$B$4)+G12 | N12: =H12*Assumptions!$B$2+IF(A12=1,Assumptions!$B$5,0) | O12: =I12*Assumptions!$B$2 | P12: =K12-M12-N12-O12 | Q12: =Q11+P12 | R12: =MAX(R11,-Q12)
A13: 12 | B13: 1 | C13: 700 | D13: 2 | E13: 450 | F13: 0.7 | G13: 0 | H13: 100 | I13: 60 | J13: =B13+D13 | K13: =(B13*C13+D13*E13)*Assumptions!$B$2 | L13: =IFERROR(K13/J13,0) | M13: =K13*(Assumptions!$B$3*F13+Assumptions!$B$4)+G13 | N13: =H13*Assumptions!$B$2+IF(A13=1,Assumptions!$B$5,0) | O13: =I13*Assumptions!$B$2 | P13: =K13-M13-N13-O13 | Q13: =Q12+P13 | R13: =MAX(R12,-Q13)
A15: Total | K15: =SUM(K2:K13) | M15: =SUM(M2:M13) | N15: =SUM(N2:N13) | O15: =SUM(O2:O13) | P15: =SUM(P2:P13)

Sheet Base
A1: Month | B1: Projects | C1: Avg project USD | D1: Retainers | E1: Avg retainer USD | F1: Upwork share | G1: Contractor PKR | H1: Software USD | I1: Marketing USD | J1: Paying customers | K1: Revenue PKR | L1: Avg rev/customer PKR | M1: Direct costs PKR | N1: Software/ops PKR | O1: Marketing PKR | P1: Net profit PKR | Q1: Cumulative profit PKR | R1: Cumulative investment PKR
A2: 1 | B2: 0 | C2: 0 | D2: 0 | E2: 0 | F2: 1 | G2: 0 | H2: 90 | I2: 60 | J2: =B2+D2 | K2: =(B2*C2+D2*E2)*Assumptions!$B$2 | L2: =IFERROR(K2/J2,0) | M2: =K2*(Assumptions!$B$3*F2+Assumptions!$B$4)+G2 | N2: =H2*Assumptions!$B$2+IF(A2=1,Assumptions!$B$5,0) | O2: =I2*Assumptions!$B$2 | P2: =K2-M2-N2-O2 | Q2: =P2 | R2: =MAX(0,-Q2)
A3: 2 | B3: 1 | C3: 400 | D3: 0 | E3: 0 | F3: 1 | G3: 0 | H3: 140 | I3: 160 | J3: =B3+D3 | K3: =(B3*C3+D3*E3)*Assumptions!$B$2 | L3: =IFERROR(K3/J3,0) | M3: =K3*(Assumptions!$B$3*F3+Assumptions!$B$4)+G3 | N3: =H3*Assumptions!$B$2+IF(A3=1,Assumptions!$B$5,0) | O3: =I3*Assumptions!$B$2 | P3: =K3-M3-N3-O3 | Q3: =Q2+P3 | R3: =MAX(R2,-Q3)
A4: 3 | B4: 1 | C4: 600 | D4: 0 | E4: 0 | F4: 1 | G4: 0 | H4: 140 | I4: 160 | J4: =B4+D4 | K4: =(B4*C4+D4*E4)*Assumptions!$B$2 | L4: =IFERROR(K4/J4,0) | M4: =K4*(Assumptions!$B$3*F4+Assumptions!$B$4)+G4 | N4: =H4*Assumptions!$B$2+IF(A4=1,Assumptions!$B$5,0) | O4: =I4*Assumptions!$B$2 | P4: =K4-M4-N4-O4 | Q4: =Q3+P4 | R4: =MAX(R3,-Q4)
A5: 4 | B5: 2 | C5: 650 | D5: 0 | E5: 0 | F5: 0.9 | G5: 0 | H5: 140 | I5: 160 | J5: =B5+D5 | K5: =(B5*C5+D5*E5)*Assumptions!$B$2 | L5: =IFERROR(K5/J5,0) | M5: =K5*(Assumptions!$B$3*F5+Assumptions!$B$4)+G5 | N5: =H5*Assumptions!$B$2+IF(A5=1,Assumptions!$B$5,0) | O5: =I5*Assumptions!$B$2 | P5: =K5-M5-N5-O5 | Q5: =Q4+P5 | R5: =MAX(R4,-Q5)
A6: 5 | B6: 2 | C6: 750 | D6: 1 | E6: 500 | F6: 0.8 | G6: 0 | H6: 150 | I6: 180 | J6: =B6+D6 | K6: =(B6*C6+D6*E6)*Assumptions!$B$2 | L6: =IFERROR(K6/J6,0) | M6: =K6*(Assumptions!$B$3*F6+Assumptions!$B$4)+G6 | N6: =H6*Assumptions!$B$2+IF(A6=1,Assumptions!$B$5,0) | O6: =I6*Assumptions!$B$2 | P6: =K6-M6-N6-O6 | Q6: =Q5+P6 | R6: =MAX(R5,-Q6)
A7: 6 | B7: 2 | C7: 800 | D7: 1 | E7: 500 | F7: 0.7 | G7: 0 | H7: 150 | I7: 180 | J7: =B7+D7 | K7: =(B7*C7+D7*E7)*Assumptions!$B$2 | L7: =IFERROR(K7/J7,0) | M7: =K7*(Assumptions!$B$3*F7+Assumptions!$B$4)+G7 | N7: =H7*Assumptions!$B$2+IF(A7=1,Assumptions!$B$5,0) | O7: =I7*Assumptions!$B$2 | P7: =K7-M7-N7-O7 | Q7: =Q6+P7 | R7: =MAX(R6,-Q7)
A8: 7 | B8: 2 | C8: 850 | D8: 2 | E8: 550 | F8: 0.6 | G8: 60000 | H8: 150 | I8: 180 | J8: =B8+D8 | K8: =(B8*C8+D8*E8)*Assumptions!$B$2 | L8: =IFERROR(K8/J8,0) | M8: =K8*(Assumptions!$B$3*F8+Assumptions!$B$4)+G8 | N8: =H8*Assumptions!$B$2+IF(A8=1,Assumptions!$B$5,0) | O8: =I8*Assumptions!$B$2 | P8: =K8-M8-N8-O8 | Q8: =Q7+P8 | R8: =MAX(R7,-Q8)
A9: 8 | B9: 2 | C9: 900 | D9: 2 | E9: 600 | F9: 0.6 | G9: 60000 | H9: 150 | I9: 180 | J9: =B9+D9 | K9: =(B9*C9+D9*E9)*Assumptions!$B$2 | L9: =IFERROR(K9/J9,0) | M9: =K9*(Assumptions!$B$3*F9+Assumptions!$B$4)+G9 | N9: =H9*Assumptions!$B$2+IF(A9=1,Assumptions!$B$5,0) | O9: =I9*Assumptions!$B$2 | P9: =K9-M9-N9-O9 | Q9: =Q8+P9 | R9: =MAX(R8,-Q9)
A10: 9 | B10: 2 | C10: 950 | D10: 3 | E10: 600 | F10: 0.5 | G10: 80000 | H10: 160 | I10: 200 | J10: =B10+D10 | K10: =(B10*C10+D10*E10)*Assumptions!$B$2 | L10: =IFERROR(K10/J10,0) | M10: =K10*(Assumptions!$B$3*F10+Assumptions!$B$4)+G10 | N10: =H10*Assumptions!$B$2+IF(A10=1,Assumptions!$B$5,0) | O10: =I10*Assumptions!$B$2 | P10: =K10-M10-N10-O10 | Q10: =Q9+P10 | R10: =MAX(R9,-Q10)
A11: 10 | B11: 2 | C11: 1000 | D11: 3 | E11: 650 | F11: 0.5 | G11: 80000 | H11: 160 | I11: 200 | J11: =B11+D11 | K11: =(B11*C11+D11*E11)*Assumptions!$B$2 | L11: =IFERROR(K11/J11,0) | M11: =K11*(Assumptions!$B$3*F11+Assumptions!$B$4)+G11 | N11: =H11*Assumptions!$B$2+IF(A11=1,Assumptions!$B$5,0) | O11: =I11*Assumptions!$B$2 | P11: =K11-M11-N11-O11 | Q11: =Q10+P11 | R11: =MAX(R10,-Q11)
A12: 11 | B12: 2 | C12: 1050 | D12: 4 | E12: 650 | F12: 0.4 | G12: 100000 | H12: 160 | I12: 200 | J12: =B12+D12 | K12: =(B12*C12+D12*E12)*Assumptions!$B$2 | L12: =IFERROR(K12/J12,0) | M12: =K12*(Assumptions!$B$3*F12+Assumptions!$B$4)+G12 | N12: =H12*Assumptions!$B$2+IF(A12=1,Assumptions!$B$5,0) | O12: =I12*Assumptions!$B$2 | P12: =K12-M12-N12-O12 | Q12: =Q11+P12 | R12: =MAX(R11,-Q12)
A13: 12 | B13: 2 | C13: 1100 | D13: 4 | E13: 650 | F13: 0.4 | G13: 100000 | H13: 160 | I13: 200 | J13: =B13+D13 | K13: =(B13*C13+D13*E13)*Assumptions!$B$2 | L13: =IFERROR(K13/J13,0) | M13: =K13*(Assumptions!$B$3*F13+Assumptions!$B$4)+G13 | N13: =H13*Assumptions!$B$2+IF(A13=1,Assumptions!$B$5,0) | O13: =I13*Assumptions!$B$2 | P13: =K13-M13-N13-O13 | Q13: =Q12+P13 | R13: =MAX(R12,-Q13)
A15: Total | K15: =SUM(K2:K13) | M15: =SUM(M2:M13) | N15: =SUM(N2:N13) | O15: =SUM(O2:O13) | P15: =SUM(P2:P13)

Sheet Aggressive
A1: Month | B1: Projects | C1: Avg project USD | D1: Retainers | E1: Avg retainer USD | F1: Upwork share | G1: Contractor PKR | H1: Software USD | I1: Marketing USD | J1: Paying customers | K1: Revenue PKR | L1: Avg rev/customer PKR | M1: Direct costs PKR | N1: Software/ops PKR | O1: Marketing PKR | P1: Net profit PKR | Q1: Cumulative profit PKR | R1: Cumulative investment PKR
A2: 1 | B2: 0 | C2: 0 | D2: 0 | E2: 0 | F2: 1 | G2: 0 | H2: 100 | I2: 80 | J2: =B2+D2 | K2: =(B2*C2+D2*E2)*Assumptions!$B$2 | L2: =IFERROR(K2/J2,0) | M2: =K2*(Assumptions!$B$3*F2+Assumptions!$B$4)+G2 | N2: =H2*Assumptions!$B$2+IF(A2=1,Assumptions!$B$5,0) | O2: =I2*Assumptions!$B$2 | P2: =K2-M2-N2-O2 | Q2: =P2 | R2: =MAX(0,-Q2)
A3: 2 | B3: 1 | C3: 600 | D3: 0 | E3: 0 | F3: 0.9 | G3: 0 | H3: 180 | I3: 200 | J3: =B3+D3 | K3: =(B3*C3+D3*E3)*Assumptions!$B$2 | L3: =IFERROR(K3/J3,0) | M3: =K3*(Assumptions!$B$3*F3+Assumptions!$B$4)+G3 | N3: =H3*Assumptions!$B$2+IF(A3=1,Assumptions!$B$5,0) | O3: =I3*Assumptions!$B$2 | P3: =K3-M3-N3-O3 | Q3: =Q2+P3 | R3: =MAX(R2,-Q3)
A4: 3 | B4: 2 | C4: 800 | D4: 1 | E4: 500 | F4: 0.8 | G4: 0 | H4: 180 | I4: 250 | J4: =B4+D4 | K4: =(B4*C4+D4*E4)*Assumptions!$B$2 | L4: =IFERROR(K4/J4,0) | M4: =K4*(Assumptions!$B$3*F4+Assumptions!$B$4)+G4 | N4: =H4*Assumptions!$B$2+IF(A4=1,Assumptions!$B$5,0) | O4: =I4*Assumptions!$B$2 | P4: =K4-M4-N4-O4 | Q4: =Q3+P4 | R4: =MAX(R3,-Q4)
A5: 4 | B5: 3 | C5: 900 | D5: 1 | E5: 550 | F5: 0.7 | G5: 0 | H5: 200 | I5: 250 | J5: =B5+D5 | K5: =(B5*C5+D5*E5)*Assumptions!$B$2 | L5: =IFERROR(K5/J5,0) | M5: =K5*(Assumptions!$B$3*F5+Assumptions!$B$4)+G5 | N5: =H5*Assumptions!$B$2+IF(A5=1,Assumptions!$B$5,0) | O5: =I5*Assumptions!$B$2 | P5: =K5-M5-N5-O5 | Q5: =Q4+P5 | R5: =MAX(R4,-Q5)
A6: 5 | B6: 3 | C6: 1000 | D6: 2 | E6: 600 | F6: 0.6 | G6: 60000 | H6: 200 | I6: 300 | J6: =B6+D6 | K6: =(B6*C6+D6*E6)*Assumptions!$B$2 | L6: =IFERROR(K6/J6,0) | M6: =K6*(Assumptions!$B$3*F6+Assumptions!$B$4)+G6 | N6: =H6*Assumptions!$B$2+IF(A6=1,Assumptions!$B$5,0) | O6: =I6*Assumptions!$B$2 | P6: =K6-M6-N6-O6 | Q6: =Q5+P6 | R6: =MAX(R5,-Q6)
A7: 6 | B7: 3 | C7: 1100 | D7: 3 | E7: 650 | F7: 0.5 | G7: 80000 | H7: 220 | I7: 300 | J7: =B7+D7 | K7: =(B7*C7+D7*E7)*Assumptions!$B$2 | L7: =IFERROR(K7/J7,0) | M7: =K7*(Assumptions!$B$3*F7+Assumptions!$B$4)+G7 | N7: =H7*Assumptions!$B$2+IF(A7=1,Assumptions!$B$5,0) | O7: =I7*Assumptions!$B$2 | P7: =K7-M7-N7-O7 | Q7: =Q6+P7 | R7: =MAX(R6,-Q7)
A8: 7 | B8: 3 | C8: 1200 | D8: 4 | E8: 700 | F8: 0.5 | G8: 120000 | H8: 220 | I8: 350 | J8: =B8+D8 | K8: =(B8*C8+D8*E8)*Assumptions!$B$2 | L8: =IFERROR(K8/J8,0) | M8: =K8*(Assumptions!$B$3*F8+Assumptions!$B$4)+G8 | N8: =H8*Assumptions!$B$2+IF(A8=1,Assumptions!$B$5,0) | O8: =I8*Assumptions!$B$2 | P8: =K8-M8-N8-O8 | Q8: =Q7+P8 | R8: =MAX(R7,-Q8)
A9: 8 | B9: 3 | C9: 1300 | D9: 5 | E9: 700 | F9: 0.4 | G9: 150000 | H9: 250 | I9: 350 | J9: =B9+D9 | K9: =(B9*C9+D9*E9)*Assumptions!$B$2 | L9: =IFERROR(K9/J9,0) | M9: =K9*(Assumptions!$B$3*F9+Assumptions!$B$4)+G9 | N9: =H9*Assumptions!$B$2+IF(A9=1,Assumptions!$B$5,0) | O9: =I9*Assumptions!$B$2 | P9: =K9-M9-N9-O9 | Q9: =Q8+P9 | R9: =MAX(R8,-Q9)
A10: 9 | B10: 3 | C10: 1400 | D10: 5 | E10: 750 | F10: 0.4 | G10: 180000 | H10: 250 | I10: 400 | J10: =B10+D10 | K10: =(B10*C10+D10*E10)*Assumptions!$B$2 | L10: =IFERROR(K10/J10,0) | M10: =K10*(Assumptions!$B$3*F10+Assumptions!$B$4)+G10 | N10: =H10*Assumptions!$B$2+IF(A10=1,Assumptions!$B$5,0) | O10: =I10*Assumptions!$B$2 | P10: =K10-M10-N10-O10 | Q10: =Q9+P10 | R10: =MAX(R9,-Q10)
A11: 10 | B11: 3 | C11: 1400 | D11: 6 | E11: 750 | F11: 0.3 | G11: 220000 | H11: 250 | I11: 400 | J11: =B11+D11 | K11: =(B11*C11+D11*E11)*Assumptions!$B$2 | L11: =IFERROR(K11/J11,0) | M11: =K11*(Assumptions!$B$3*F11+Assumptions!$B$4)+G11 | N11: =H11*Assumptions!$B$2+IF(A11=1,Assumptions!$B$5,0) | O11: =I11*Assumptions!$B$2 | P11: =K11-M11-N11-O11 | Q11: =Q10+P11 | R11: =MAX(R10,-Q11)
A12: 11 | B12: 3 | C12: 1500 | D12: 7 | E12: 800 | F12: 0.3 | G12: 260000 | H12: 280 | I12: 400 | J12: =B12+D12 | K12: =(B12*C12+D12*E12)*Assumptions!$B$2 | L12: =IFERROR(K12/J12,0) | M12: =K12*(Assumptions!$B$3*F12+Assumptions!$B$4)+G12 | N12: =H12*Assumptions!$B$2+IF(A12=1,Assumptions!$B$5,0) | O12: =I12*Assumptions!$B$2 | P12: =K12-M12-N12-O12 | Q12: =Q11+P12 | R12: =MAX(R11,-Q12)
A13: 12 | B13: 3 | C13: 1500 | D13: 8 | E13: 800 | F13: 0.3 | G13: 300000 | H13: 280 | I13: 400 | J13: =B13+D13 | K13: =(B13*C13+D13*E13)*Assumptions!$B$2 | L13: =IFERROR(K13/J13,0) | M13: =K13*(Assumptions!$B$3*F13+Assumptions!$B$4)+G13 | N13: =H13*Assumptions!$B$2+IF(A13=1,Assumptions!$B$5,0) | O13: =I13*Assumptions!$B$2 | P13: =K13-M13-N13-O13 | Q13: =Q12+P13 | R13: =MAX(R12,-Q13)
A15: Total | K15: =SUM(K2:K13) | M15: =SUM(M2:M13) | N15: =SUM(N2:N13) | O15: =SUM(O2:O13) | P15: =SUM(P2:P13)

Sheet Opportunity Scoring
A1: Idea | B1: Market demand | C1: Profitability | D1: Low capital | E1: Ease of start | F1: Skill fit | G1: Intl earning | H1: Scalability | I1: Competition (10=low) | J1: Speed to revenue | K1: Long-term potential | L1: Weighted score
A2: WEIGHTS | B2: 0.1 | C2: 0.1 | D2: 0.07 | E2: 0.08 | F2: 0.15 | G2: 0.12 | H2: 0.1 | I2: 0.08 | J2: 0.1 | K2: 0.1
A3: 1. Planning & Plant Performance Control Tower (productized Power BI for SME manufacturers) | B3: 8 | C3: 8 | D3: 9 | E3: 7 | F3: 10 | G3: 9 | H3: 7 | I3: 6 | J3: 7 | K3: 8 | L3: =SUMPRODUCT(B3:K3,$B$2:$K$2)
A4: 2. Fractional S&OP / Supply Planning Analyst (retainer) | B4: 7 | C4: 8 | D4: 10 | E4: 6 | F4: 10 | G4: 8 | H4: 5 | I4: 7 | J4: 6 | K4: 7 | L4: =SUMPRODUCT(B4:K4,$B$2:$K$2)
A5: 3. Inventory & SKU Health Analytics for DTC/Amazon brands | B5: 8 | C5: 7 | D5: 9 | E5: 6 | F5: 8 | G5: 9 | H5: 7 | I5: 5 | J5: 6 | K5: 7 | L5: =SUMPRODUCT(B5:K5,$B$2:$K$2)
A6: 4. Excel / Power Query reporting automation (productized gigs) | B6: 8 | C6: 6 | D6: 10 | E6: 9 | F6: 9 | G6: 8 | H6: 5 | I6: 3 | J6: 9 | K6: 5 | L6: =SUMPRODUCT(B6:K6,$B$2:$K$2)
A7: 5. Power BI / Excel KPI template store (digital products) | B7: 6 | C7: 5 | D7: 9 | E7: 7 | F7: 9 | G7: 9 | H7: 9 | I7: 4 | J7: 5 | K7: 6 | L7: =SUMPRODUCT(B7:K7,$B$2:$K$2)
A8: 6. OEE & downtime micro-SaaS for small factories | B8: 6 | C8: 8 | D8: 6 | E8: 4 | F8: 8 | G8: 7 | H8: 9 | I8: 5 | J8: 3 | K8: 8 | L8: =SUMPRODUCT(B8:K8,$B$2:$K$2)
A9: 7. Rough-cut capacity planner micro-SaaS for job shops | B9: 5 | C9: 8 | D9: 6 | E9: 3 | F9: 9 | G9: 7 | H9: 9 | I9: 6 | J9: 2 | K9: 7 | L9: =SUMPRODUCT(B9:K9,$B$2:$K$2)
A10: 8. KPI / Balanced Scorecard office for GCC SMEs | B10: 7 | C10: 8 | D10: 10 | E10: 5 | F10: 10 | G10: 8 | H10: 4 | I10: 6 | J10: 5 | K10: 7 | L10: =SUMPRODUCT(B10:K10,$B$2:$K$2)
A11: 9. AI document extraction for freight forwarders | B11: 8 | C11: 8 | D11: 9 | E11: 6 | F11: 6 | G11: 9 | H11: 7 | I11: 4 | J11: 6 | K11: 6 | L11: =SUMPRODUCT(B11:K11,$B$2:$K$2)
A12: 10. ESG & carbon data reporting for South-Asian textile exporters | B12: 7 | C12: 7 | D12: 9 | E12: 5 | F12: 7 | G12: 5 | H12: 6 | I12: 7 | J12: 4 | K12: 8 | L12: =SUMPRODUCT(B12:K12,$B$2:$K$2)
A13: 11. Remote SAP PP / IBP functional support | B13: 7 | C13: 7 | D13: 10 | E13: 6 | F13: 8 | G13: 8 | H13: 3 | I13: 5 | J13: 6 | K13: 6 | L13: =SUMPRODUCT(B13:K13,$B$2:$K$2)
A14: 12. White-label BI delivery for ERP partners & BI agencies | B14: 8 | C14: 6 | D14: 10 | E14: 6 | F14: 9 | G14: 9 | H14: 6 | I14: 6 | J14: 6 | K14: 6 | L14: =SUMPRODUCT(B14:K14,$B$2:$K$2)
... A22: 20. Spreadsheet MRP/BOM toolkit for small makers | B22: 6 | C22: 5 | D22: 9 | E22: 7 | F22: 8 | G22: 9 | H22: 8 | I22: 4 | J22: 6 | K22: 5 | L22: =SUMPRODUCT(B22:K22,$B$2:$K$2)

Sheet CRM Pipeline
A1: Lead ID | B1: Company | C1: Country | D1: Industry | E1: Revenue band | F1: ERP | G1: Contact name | H1: Title | I1: LinkedIn URL | J1: Email | K1: Source | L1: Trigger / hook | M1: Stage | N1: First touch date | O1: Last touch date | P1: Next action | Q1: Next action date | R1: Touches | S1: Deal value USD | T1: Probability | U1: Weighted USD | V1: Notes
A2: L001 | B2: (example) Acme Fasteners Ltd | M2: 2-Contacted | S2: 1200 | T2: =IFERROR(VLOOKUP(M2,Lists!$A$1:$B$8,2,FALSE),"") | U2: =IFERROR(S2*T2,"")
T3: =IFERROR(VLOOKUP(M3,Lists!$A$1:$B$8,2,FALSE),"") | U3: =IFERROR(S3*T3,"")
T4: =IFERROR(VLOOKUP(M4,Lists!$A$1:$B$8,2,FALSE),"") | U4: =IFERROR(S4*T4,"")
T5: =IFERROR(VLOOKUP(M5,Lists!$A$1:$B$8,2,FALSE),"") | U5: =IFERROR(S5*T5,"")
T6: =IFERROR(VLOOKUP(M6,Lists!$A$1:$B$8,2,FALSE),"") | U6: =IFERROR(S6*T6,"")
T7: =IFERROR(VLOOKUP(M7,Lists!$A$1:$B$8,2,FALSE),"") | U7: =IFERROR(S7*T7,"")
T8: =IFERROR(VLOOKUP(M8,Lists!$A$1:$B$8,2,FALSE),"") | U8: =IFERROR(S8*T8,"")
T9: =IFERROR(VLOOKUP(M9,Lists!$A$1:$B$8,2,FALSE),"") | U9: =IFERROR(S9*T9,"")
T10: =IFERROR(VLOOKUP(M10,Lists!$A$1:$B$8,2,FALSE),"") | U10: =IFERROR(S10*T10,"")
T11: =IFERROR(VLOOKUP(M11,Lists!$A$1:$B$8,2,FALSE),"") | U11: =IFERROR(S11*T11,"")
T12: =IFERROR(VLOOKUP(M12,Lists!$A$1:$B$8,2,FALSE),"") | U12: =IFERROR(S12*T12,"")
T13: =IFERROR(VLOOKUP(M13,Lists!$A$1:$B$8,2,FALSE),"") | U13: =IFERROR(S13*T13,"")
T14: =IFERROR(VLOOKUP(M14,Lists!$A$1:$B$8,2,FALSE),"") | U14: =IFERROR(S14*T14,"")
... T300: =IFERROR(VLOOKUP(M300,Lists!$A$1:$B$8,2,FALSE),"") | U300: =IFERROR(S300*T300,"")

Sheet Lists
A1: 1-Identified | B1: 0.02
A2: 2-Contacted | B2: 0.05
A3: 3-Replied | B3: 0.15
A4: 4-Discovery booked | B4: 0.3
A5: 5-Diagnostic proposed | B5: 0.5
A6: 6-Won | B6: 1
A7: 7-Lost | B7: 0
A8: 8-Nurture | B8: 0.03

Sheet 90-Day Tracker
A1: Week | B1: Phase | C1: Outcome target | D1: Prospects added | E1: Touches sent | F1: Replies | G1: Discovery calls | H1: Proposals | I1: Wins | J1: Revenue USD | K1: Hours spent | L1: Status | M1: Blocker / learning
A2: 1 | B2: Foundation | C2: Offer, demo, site, payments live; 50-lead list
A3: 2 | B3: Acquisition system | C3: 100 touches; 3 Upwork proposals/day
A4: 3 | B4: Acquisition system | C4: 150 touches; 2 discovery calls
A5: 4 | B5: Acquisition system | C5: 150 touches; first proposal
A6: 5 | B6: First customers | C6: First paid diagnostic
A7: 6 | B7: First customers | C7: Deliver + testimonial
A8: 7 | B8: First customers | C8: Case study #1 published
A9: 8 | B9: First customers | C9: 2nd/3rd client; raise price 20%
A10: 9 | B10: First customers | C10: First retainer signed
A11: 10 | B11: Scale & productize | C11: SOPs v1 + contractor trial
A12: 11 | B12: Scale & productize | C12: Partner channel: 2 ERP partners
A13: 12 | B13: Scale & productize | C13: Retainer #2; automation of weekly pack
A14: 13 | B14: Scale & productize | C14: Review: kill / double-down decision
A15: Total | D15: =SUM(D2:D14) | E15: =SUM(E2:E14) | F15: =SUM(F2:F14) | G15: =SUM(G2:G14) | H15: =SUM(H2:H14) | I15: =SUM(I2:I14) | J15: =SUM(J2:J14) | K15: =SUM(K2:K14)
